microprice/__init__.py
microprice-0.1.1.dist-info/LICENSE.md
microprice-0.1.1.dist-info/METADATA
microprice-0.1.1.dist-info/WHEEL
microprice-0.1.1.dist-info/top_level.txt
microprice-0.1.1.dist-info/RECORD
