Metadata-Version: 2.1
Name: microprice
Version: 0.1.1
Summary: A Jax implementation of Micro-Price: A High Frequency Estimator of Future Prices.
Home-page: https://github.com/alexandrebrilhante/quantnet
Author: Alexandre Brilhante
Author-email: alexandre.brilhante@gmail.com
Project-URL: Bug Tracker, https://github.com/alexandrebrilhante/microprice/issues
Classifier: Programming Language :: Python :: 3
Classifier: License :: OSI Approved :: MIT License
Classifier: Operating System :: OS Independent
Requires-Python: >=3.8
License-File: LICENSE.md
